{
    "sourceFile": "Modules/User/database/seeders/RolesSeeder.php",
    "activeCommit": 0,
    "commits": [
        {
            "activePatchIndex": 1,
            "patches": [
                {
                    "date": 1759748417057,
                    "content": "Index: \n===================================================================\n--- \n+++ \n"
                },
                {
                    "date": 1759827908462,
                    "content": "Index: \n===================================================================\n--- \n+++ \n@@ -1,6 +1,6 @@\n <?php\n-namespace Modules\\User\\Database\\Seeders;\n+namespace Modules\\User\\database\\seeders;\n \n use Illuminate\\Database\\Seeder;\n use Spatie\\Permission\\Models\\Role;\n \n"
                }
            ],
            "date": 1759748417057,
            "name": "Commit-0",
            "content": "<?php\nnamespace Modules\\User\\Database\\Seeders;\n\nuse Illuminate\\Database\\Seeder;\nuse Spatie\\Permission\\Models\\Role;\n\nclass RolesSeeder extends Seeder\n{\n    /**\n     * Run the database seeds.\n     *\n     * @return void\n     */\n    public function run()\n    {\n        Role::create(['name'=>'admin']);\n        Role::create(['name'=>'host']);\n        Role::create(['name'=>'customer']);\n    }\n}\n"
        }
    ]
}